README.rst
setup.py
bytearound/__init__.py
bytearound/code_object.py
bytearound/debug.py
bytearound/generator.py
bytearound/ops.py
bytearound/parser.py
bytearound.egg-info/PKG-INFO
bytearound.egg-info/SOURCES.txt
bytearound.egg-info/dependency_links.txt
bytearound.egg-info/top_level.txt