Metadata-Version: 1.1
Name: bytearound
Version: 0.2
Summary: Python module to handle bytecode
Home-page: https://github.com/JelleZijlstra/bytearound
Author: Jelle Zijlstra
Author-email: jelle.zijlstra@gmail.com
License: Apache 2.0 license
Platform: UNKNOWN
Classifier: Development Status :: 3 - Alpha
Classifier: Intended Audience :: Developers
Classifier: Topic :: Software Development :: Libraries :: Python Modules
Classifier: License :: OSI Approved :: Apache Software License
Classifier: Programming Language :: Python :: 2.7
